<root>
    <UNB>
        <S001>
            <E0001>UNOC</E0001>
            <E0002>2</E0002>
        </S001>
        <S002>
            <E0004>YOURID</E0004>
            <E0007>01</E0007>
        </S002>
        <S003>
            <E0010>CARGOSMART</E0010>
            <E0007>01</E0007>
        </S003>
        <S004>
            <E0017>081210</E0017>
            <E0019>0856</E0019>
        </S004>
        <S0020>78043</S0020>
        <S0022>IFTMIN</S0022>
    </UNB>
    <UNH>
        <S0062>780430001</S0062>
        <S009>
            <E0065>IFTMIN</E0065>
            <E0052>D</E0052>
            <E0054>99B</E0054>
            <E0051>UN</E0051>
        </S009>
    </UNH>
    <BGM>
        <C002>
            <E1001>340</E1001>
        </C002>
        <C106>
            <E1004>2009921360</E1004>
        </C106>
        <C1225>9</C1225>
    </BGM>
    <TSR>
        <C536>
            <E4065>30</E4065>
        </C536>
        <C233>
            <E7273>3</E7273>
        </C233>
    </TSR>
    <FTX>
        <C4451>AAS</C4451>
        <C108>
            <E4440>Freight Collect</E4440>
        </C108>
    </FTX>
    <FTX>
        <C4451>BLC</C4451>
        <C108>
            <E4440>THIS SHIPMENT CONTAINS NO WOOD PACKAGE MATERIAL IN CONTAINER</E4440>
        </C108>
    </FTX>
    <CNT>
        <C270>
            <E6069>7</E6069>
            <E6066>671.5</E6066>
            <E6411>KGM</E6411>
        </C270>
    </CNT>
    <CNT>
        <C270>
            <E6069>11</E6069>
            <E6066>500</E6066>
        </C270>
    </CNT>
    <CNT>
        <C270>
            <E6069>15</E6069>
            <E6066>48</E6066>
            <E6411>CBM</E6411>
        </C270>
    </CNT>
    <CNT>
        <C270>
            <E6069>16</E6069>
            <E6066>2</E6066>
        </C270>
    </CNT>
    <group_1>
        <LOC>
            <C3227>57</C3227>
            <C517>
                <E3225>USNYC</E3225>
                <E1131>145</E1131>
                <E3224>NEW YORK</E3224>
            </C517>
        </LOC>
    </group_1>
    <group_1>
        <LOC>
            <C3227>73</C3227>
            <C517>
                <E3225>USNYC</E3225>
                <E1131>145</E1131>
                <E3224>NEW YORK</E3224>
            </C517>
        </LOC>
        <DTM>
            <C507>
                <E2005>95</E2005>
                <E2380>20150313</E2380>
                <E2379>102</E2379>
            </C507>
        </DTM>
    </group_1>
    <group_3>
        <RFF>
            <C506>
                <E1153>BN</E1153>
                <E1154>387590403A</E1154>
            </C506>
        </RFF>
    </group_3>
    <group_3>
        <RFF>
            <C506>
                <E1153>SI</E1153>
                <E1154>2009921360</E1154>
            </C506>
        </RFF>
    </group_3>
    <group_6>
        <CPI>
            <C229>
                <E5237>4</E5237>
            </C229>
            <C4237>C</C4237>
        </CPI>
    </group_6>
    <group_8>
        <TDT>
            <C8051>20</C8051>
            <C8028>018East</C8028>
            <C220>
                <E8067>1</E8067>
            </C220>
            <C040>
                <E3127>COSU</E3127>
                <E1131>172</E1131>
            </C040>
            <C222>
                <E8213>9235074</E8213>
                <E1131>L</E1131>
                <E8212>CMA VESSEL</E8212>
            </C222>
        </TDT>
        <group_9>
            <LOC>
                <C3227>9</C3227>
                <C517>
                    <E3225>SGSIN</E3225>
                    <E3055>6</E3055>
                    <E3224>SINGAPORE</E3224>
                </C517>
            </LOC>
        </group_9>
        <group_9>
            <LOC>
                <C3227>11</C3227>
                <C517>
                    <E3225>USLAX</E3225>
                    <E3055>6</E3055>
                    <E3224>LOS ANGELES</E3224>
                </C517>
            </LOC>
        </group_9>
        <group_9>
            <LOC>
                <C3227>88</C3227>
                <C517>
                    <E3225>THLCH</E3225>
                    <E3055>6</E3055>
                    <E3224>LAEM CHABANG</E3224>
                </C517>
            </LOC>
        </group_9>
        <group_9>
            <LOC>
                <C3227>7</C3227>
                <C517>
                    <E3225>USCHI</E3225>
                    <E3055>6</E3055>
                    <E3224>CHICAGO</E3224>
                </C517>
            </LOC>
        </group_9>
    </group_8>
    <group_11>
        <NAD>
            <C3035>CA</C3035>
            <C082>
                <E3039>COSU</E3039>
                <E3040>160</E3040>
                <E3041>86</E3041>
            </C082>
        </NAD>
    </group_11>
    <group_11>
        <NAD>
            <C3035>SH</C3035>
            <C080>
                <E3036>SHIPPER COMPANY NAME</E3036>
            </C080>
            <C059>
                <E3042>SHIPPING COMPANY ADDRESS LINE1</E3042>
                <E3042>SHIPPING COMPANY ADDRESS LINE2</E3042>
            </C059>
        </NAD>
        <group_13>
            <DOC>
                <C002>
                    <E1001>707</E1001>
                </C002>
                <C503>
                    <E1373>26</E1373>
                </C503>
                <C3153>EM</C3153>
                <C1220>3</C1220>
            </DOC>
        </group_13>
    </group_11>
    <group_11>
        <NAD>
            <C3035>FW</C3035>
            <C080>
                <E3036>FORWARDER COMPANY NAME</E3036>
            </C080>
            <C059>
                <E3042>FORWARDER COMPANY ADDRESS LINE1</E3042>
                <E3042>FORWARDER COMPANY ADDRESS LINE2</E3042>
            </C059>
        </NAD>
    </group_11>
    <group_11>
        <NAD>
            <C3035>CN</C3035>
            <C080>
                <E3036>CONSIGNEE COMPANY NAME</E3036>
            </C080>
            <C059>
                <E3042>CONSIGNEE COMPANY ADDRESS LINE1</E3042>
                <E3042>CONSIGNEE COMPANY ADDRESS LINE2</E3042>
            </C059>
        </NAD>
        <group_13>
            <DOC>
                <C002>
                    <E1001>705</E1001>
                </C002>
                <C503>
                    <E1373>26</E1373>
                </C503>
                <C3153>EM</C3153>
                <C1220>3</C1220>
            </DOC>
        </group_13>
    </group_11>
    <group_11>
        <NAD>
            <C3035>SI</C3035>
            <C082>
                <E3039>OFFICECODE</E3039>
            </C082>
            <C080>
                <E3036>SI SUBMITTER COMPANY NAME</E3036>
            </C080>
            <C059>
                <E3042>REQUEST COMPANY ADDRESS LINE1</E3042>
                <E3042>REQUEST COMPANY ADDRESS LINE2</E3042>
            </C059>
        </NAD>
        <group_12>
            <CTA>
                <C3139>IC</C3139>
                <C056>
                    <E3412>JAMES YU</E3412>
                </C056>
            </CTA>
            <COM>
                <C076>
                    <E3148>86-121-522153251</E3148>
                    <E3155>TE</E3155>
                </C076>
            </COM>
            <COM>
                <C076>
                    <E3148>jamesy@si_requestor.com</E3148>
                    <E3155>EM</E3155>
                </C076>
            </COM>
        </group_12>
    </group_11>
    <group_18>
        <GID>
            <C1496>1</C1496>
            <C213>
                <E7224>4</E7224>
                <E7065>PX</E7065>
            </C213>
        </GID>
        <PIA>
            <C4347>5</C4347>
            <C212>
                <E7140>903210</E7140>
                <E7143>HS</E7143>
            </C212>
        </PIA>
        <FTX>
            <C4451>AAA</C4451>
            <C108>
                <E4440>ELECTRICAL APPLIANCE PARTS, NOS</E4440>
            </C108>
        </FTX>
        <FTX>
            <C4451>AAA</C4451>
            <C108>
                <E4440>HS CODE: 903210</E4440>
            </C108>
        </FTX>
        <group_20>
            <MEA>
                <C6311>WT</C6311>
                <C502>
                    <E6313>G</E6313>
                </C502>
                <C174>
                    <E6411>KGM</E6411>
                    <E6314>471.50</E6314>
                </C174>
            </MEA>
        </group_20>
        <group_20>
            <MEA>
                <C6311>VOL</C6311>
                <C502>
                    <E6313>AAW</E6313>
                </C502>
                <C174>
                    <E6411>CBM</E6411>
                    <E6314>42</E6314>
                </C174>
            </MEA>
        </group_20>
        <group_23>
            <PCI>
                <C210>
                    <E7102>CONTAINER NO./ SEAL NO.</E7102>
                </C210>
            </PCI>
        </group_23>
        <group_29>
            <SGP>
                <C237>
                    <E8260>MOFU010462</E8260>
                </C237>
                <C7224>4</C7224>
            </SGP>
            <group_30>
                <MEA>
                    <C6311>WT</C6311>
                    <C502>
                        <E6313>G</E6313>
                    </C502>
                    <C174>
                        <E6411>KGM</E6411>
                        <E6314>371.5</E6314>
                    </C174>
                </MEA>
            </group_30>
            <group_30>
                <MEA>
                    <C6311>VOL</C6311>
                    <C502>
                        <E6313>AAW</E6313>
                    </C502>
                    <C174>
                        <E6411>CBM</E6411>
                        <E6314>40</E6314>
                    </C174>
                </MEA>
            </group_30>
        </group_29>
        <group_29>
            <SGP>
                <C237>
                    <E8260>CAXU432527</E8260>
                </C237>
                <C7224>8</C7224>
            </SGP>
            <group_30>
                <MEA>
                    <C6311>WT</C6311>
                    <C502>
                        <E6313>G</E6313>
                    </C502>
                    <C174>
                        <E6411>KGM</E6411>
                        <E6314>100</E6314>
                    </C174>
                </MEA>
            </group_30>
            <group_30>
                <MEA>
                    <C6311>VOL</C6311>
                    <C502>
                        <E6313>AAW</E6313>
                    </C502>
                    <C174>
                        <E6411>CBM</E6411>
                        <E6314>2</E6314>
                    </C174>
                </MEA>
            </group_30>
        </group_29>
    </group_18>
    <group_18>
        <GID>
            <C1496>1</C1496>
            <C213>
                <E7224>8</E7224>
                <E7065>BX</E7065>
            </C213>
        </GID>
        <PIA>
            <C4347>5</C4347>
            <C212>
                <E7140>903333</E7140>
                <E7143>HS</E7143>
            </C212>
        </PIA>
        <FTX>
            <C4451>AAA</C4451>
            <C108>
                <E4440>MACHINE PARTS, NOS</E4440>
            </C108>
        </FTX>
        <FTX>
            <C4451>AAA</C4451>
            <C108>
                <E4440>HS CODE: 903333</E4440>
            </C108>
        </FTX>
        <group_20>
            <MEA>
                <C6311>WT</C6311>
                <C502>
                    <E6313>G</E6313>
                </C502>
                <C174>
                    <E6411>KGM</E6411>
                    <E6314>200.50</E6314>
                </C174>
            </MEA>
        </group_20>
        <group_20>
            <MEA>
                <C6311>VOL</C6311>
                <C502>
                    <E6313>AAW</E6313>
                </C502>
                <C174>
                    <E6411>CBM</E6411>
                    <E6314>6</E6314>
                </C174>
            </MEA>
        </group_20>
        <group_23>
            <PCI>
                <C210>
                    <E7102>CONTAINER NO./ SEAL NO.</E7102>
                </C210>
            </PCI>
        </group_23>
        <group_29>
            <SGP>
                <C237>
                    <E8260>CAXU432527</E8260>
                </C237>
                <C7224>8</C7224>
            </SGP>
            <group_30>
                <MEA>
                    <C6311>WT</C6311>
                    <C502>
                        <E6313>G</E6313>
                    </C502>
                    <C174>
                        <E6411>KGM</E6411>
                        <E6314>200.50</E6314>
                    </C174>
                </MEA>
            </group_30>
            <group_30>
                <MEA>
                    <C6311>VOL</C6311>
                    <C502>
                        <E6313>AAW</E6313>
                    </C502>
                    <C174>
                        <E6411>CBM</E6411>
                        <E6314>6</E6314>
                    </C174>
                </MEA>
            </group_30>
        </group_29>
    </group_18>
    <group_37>
        <EQD>
            <C8053>CN</C8053>
            <C237>
                <E8260>MOFU010462</E8260>
            </C237>
            <C224>
                <E8155>22G0</E8155>
            </C224>
            <C8077>2</C8077>
        </EQD>
        <MEA>
            <C6311>WT</C6311>
            <C502>
                <E6313>G</E6313>
            </C502>
            <C174>
                <E6411>KGM</E6411>
                <E6314>371.5</E6314>
            </C174>
        </MEA>
        <MEA>
            <C6311>VOL</C6311>
            <C502>
                <E6313>AAW</E6313>
            </C502>
            <C174>
                <E6411>CBM</E6411>
                <E6314>40</E6314>
            </C174>
        </MEA>
        <SEL>
            <C9308>03739</C9308>
            <C215>
                <E9303>CA</E9303>
            </C215>
        </SEL>
    </group_37>
    <group_37>
        <EQD>
            <C8053>CN</C8053>
            <C237>
                <E8260>CAXU432527</E8260>
            </C237>
            <C224>
                <E8155>22G0</E8155>
            </C224>
            <C8077>2</C8077>
        </EQD>
        <MEA>
            <C6311>WT</C6311>
            <C502>
                <E6313>G</E6313>
            </C502>
            <C174>
                <E6411>KGM</E6411>
                <E6314>300.50</E6314>
            </C174>
        </MEA>
        <MEA>
            <C6311>VOL</C6311>
            <C502>
                <E6313>AAW</E6313>
            </C502>
            <C174>
                <E6411>CBM</E6411>
                <E6314>8</E6314>
            </C174>
        </MEA>
        <SEL>
            <C9308>03738</C9308>
            <C215>
                <E9303>CA</E9303>
            </C215>
        </SEL>
    </group_37>
    <UNT>
        <C0074>62</C0074>
        <C0062>780430001</C0062>
    </UNT>
    <UNZ>
        <C0036>1</C0036>
        <C0020>78043</C0020>
    </UNZ>
</root>